piperider_cli/SENTRY_DNS
piperider_cli/VERSION
piperider_cli/__init__.py
piperider_cli/__main__.py
piperider_cli/cli.py
piperider_cli/cloud_connector.py
piperider_cli/compare_report.py
piperider_cli/configuration.py
piperider_cli/dbtutil.py
piperider_cli/error.py
piperider_cli/exitcode.py
piperider_cli/feedback.py
piperider_cli/generate_report.py
piperider_cli/githubutil.py
piperider_cli/guide.py
piperider_cli/initializer.py
piperider_cli/recipe_executor.py
piperider_cli/runner.py
piperider_cli/statistics.py
piperider_cli/utils.py
piperider_cli/validator.py
piperider_cli/cli_utils/__init__.py
piperider_cli/cli_utils/cloud.py
piperider_cli/cli_utils/compare_with_recipe.py
piperider_cli/cli_utils/run_cmd.py
piperider_cli/cloud/__init__.py
piperider_cli/data/COMMIT
piperider_cli/data/CONFIG
piperider_cli/data/__init__.py
piperider_cli/data/piperider-init-template/config.yml
piperider_cli/data/piperider-init-template/gitignore
piperider_cli/data/report/comparison-report/asset-manifest.json
piperider_cli/data/report/comparison-report/index.html
piperider_cli/data/report/comparison-report/logo/android-chrome-192x192.png
piperider_cli/data/report/comparison-report/logo/android-chrome-512x512.png
piperider_cli/data/report/comparison-report/logo/android-icon-144x144.png
piperider_cli/data/report/comparison-report/logo/android-icon-192x192.png
piperider_cli/data/report/comparison-report/logo/android-icon-36x36.png
piperider_cli/data/report/comparison-report/logo/android-icon-48x48.png
piperider_cli/data/report/comparison-report/logo/android-icon-72x72.png
piperider_cli/data/report/comparison-report/logo/android-icon-96x96.png
piperider_cli/data/report/comparison-report/logo/apple-icon-114x114.png
piperider_cli/data/report/comparison-report/logo/apple-icon-120x120.png
piperider_cli/data/report/comparison-report/logo/apple-icon-144x144.png
piperider_cli/data/report/comparison-report/logo/apple-icon-152x152.png
piperider_nightly-0.42.0.20250102.dist-info/LICENSE
piperider_nightly-0.42.0.20250102.dist-info/METADATA
piperider_nightly-0.42.0.20250102.dist-info/WHEEL
piperider_nightly-0.42.0.20250102.dist-info/entry_points.txt
piperider_nightly-0.42.0.20250102.dist-info/top_level.txt
piperider_nightly-0.42.0.20250102.dist-info/RECORD
