Metadata-Version: 2.1
Name: piperider-nightly
Version: 0.42.0.20250102
Summary: PiperRider CLI
Home-page: https://github.com/InfuseAI/piperider
Author: InfuseAI Dev Team
Author-email: dev@infuseai.io
Project-URL: Bug Tracker, https://github.com/InfuseAI/piperider/issues
Classifier: Programming Language :: Python :: 3.8
Classifier: Programming Language :: Python :: 3.9
Classifier: Programming Language :: Python :: 3.10
Classifier: Programming Language :: Python :: 3.11
Classifier: License :: OSI Approved :: Apache Software License
Classifier: Operating System :: OS Independent
Classifier: Development Status :: 4 - Beta
Requires-Python: >=3.8
License-File: LICENSE
Requires-Dist: ruamel.yaml <0.18.0
Requires-Dist: sqlalchemy >=1.4
Requires-Dist: sentry-sdk
Requires-Dist: rich >=12.0.0
Requires-Dist: click >=7.1
Requires-Dist: python-dateutil
Requires-Dist: inquirer >=2.10.0
Requires-Dist: jinja2
Requires-Dist: jsonschema >=3.2.0
Requires-Dist: portalocker
Requires-Dist: requests >=2.28.1
Requires-Dist: requests-toolbelt >=0.9.1
Requires-Dist: deepmerge
Requires-Dist: dbt-core >=1.3
Provides-Extra: athena
Requires-Dist: PyAthena[sqlalchemy] ; extra == 'athena'
Provides-Extra: bigquery
Requires-Dist: sqlalchemy-bigquery >=1.6 ; extra == 'bigquery'
Provides-Extra: csv
Requires-Dist: duckdb >=0.4.0 ; extra == 'csv'
Requires-Dist: duckdb-engine >=0.6.1 ; extra == 'csv'
Requires-Dist: chardet >=5.0.0 ; extra == 'csv'
Provides-Extra: databricks
Requires-Dist: databricks-sql-connector ; extra == 'databricks'
Provides-Extra: dev
Requires-Dist: tox ; extra == 'dev'
Requires-Dist: pytest >=4.6 ; extra == 'dev'
Requires-Dist: pytest-flake8 ; extra == 'dev'
Requires-Dist: flake8 ==3.9.2 ; extra == 'dev'
Requires-Dist: pytest-mypy ; extra == 'dev'
Requires-Dist: pytest-cov ; extra == 'dev'
Requires-Dist: twine ; extra == 'dev'
Requires-Dist: jsonschema ; extra == 'dev'
Provides-Extra: duckdb
Requires-Dist: duckdb >=0.4.0 ; extra == 'duckdb'
Requires-Dist: duckdb-engine >=0.6.1 ; extra == 'duckdb'
Requires-Dist: chardet >=5.0.0 ; extra == 'duckdb'
Provides-Extra: parquet
Requires-Dist: duckdb >=0.4.0 ; extra == 'parquet'
Requires-Dist: duckdb-engine >=0.6.1 ; extra == 'parquet'
Requires-Dist: chardet >=5.0.0 ; extra == 'parquet'
Provides-Extra: postgres
Requires-Dist: psycopg2-binary ; extra == 'postgres'
Provides-Extra: redshift
Requires-Dist: sqlalchemy-redshift ; extra == 'redshift'
Requires-Dist: redshift-connector ; extra == 'redshift'
Requires-Dist: psycopg2-binary ; extra == 'redshift'
Requires-Dist: boto3 >=1.24.11 ; extra == 'redshift'
Provides-Extra: snowflake
Requires-Dist: snowflake-sqlalchemy >=1.4.6 ; extra == 'snowflake'
Requires-Dist: snowflake-connector-python >=2.9 ; extra == 'snowflake'
